README.md
setup.py
globomap_api_client/__init__.py
globomap_api_client/auth.py
globomap_api_client/base.py
globomap_api_client/collection.py
globomap_api_client/document.py
globomap_api_client/document_collection.py
globomap_api_client/document_edge.py
globomap_api_client/edge.py
globomap_api_client/exceptions.py
globomap_api_client/graph.py
globomap_api_client/query.py
globomap_api_client/settings.py
globomap_api_client.egg-info/PKG-INFO
globomap_api_client.egg-info/SOURCES.txt
globomap_api_client.egg-info/dependency_links.txt
globomap_api_client.egg-info/requires.txt
globomap_api_client.egg-info/top_level.txt