Metadata-Version: 1.0
Name: globomap-api-client
Version: 1.0.14
Summary: Client to GloboMAP API
Home-page: https://github.com/globocom/globomap-api-client
Author: Ederson Brilhante
Author-email: ederson.brilhante@corp.globo.com
License: UNKNOWN
Platform: UNKNOWN
